nku/__init__.py
nku/nk10.py
nku/nk100.py
nku/nk20.py
nku/nk200.py
nku/nk256.py
nku/nk30.py
nku-1.0.1.dist-info/LICENSE
nku-1.0.1.dist-info/METADATA
nku-1.0.1.dist-info/WHEEL
nku-1.0.1.dist-info/top_level.txt
nku-1.0.1.dist-info/RECORD
